mozdetect/__init__.py
mozdetect/data.py
mozdetect/telemetry_query.py
mozdetect/utils.py
mozdetect/detectors/__init__.py
mozdetect/detectors/base.py
mozdetect/detectors/cdf.py
mozdetect/detectors/cdf_squared.py
mozdetect/timeseries_detectors/__init__.py
mozdetect/timeseries_detectors/base.py
mozdetect/timeseries_detectors/cdf.py
mozdetect/timeseries_detectors/cdf_squared.py
mozdetect/timeseries_detectors/detection.py
mozdetect-0.0.9.dist-info/licenses/LICENSE
mozdetect-0.0.9.dist-info/METADATA
mozdetect-0.0.9.dist-info/WHEEL
mozdetect-0.0.9.dist-info/top_level.txt
mozdetect-0.0.9.dist-info/RECORD
