Metadata-Version: 2.4
Name: mozdetect
Version: 0.0.9
Summary: A python package used for change point detection at Mozilla.
Author-email: Gregory Mierzwinski <sparky@mozilla.com>
Requires-Python: >=3.8
License-File: LICENSE
Requires-Dist: db-dtypes>=1.3.0
Requires-Dist: google-cloud-bigquery>=3.26.0
Requires-Dist: pandas>=2.0.3
Requires-Dist: pre-commit>=3.5.0
Requires-Dist: prettytable>=3.11.0
Requires-Dist: scipy>=1.10.1
Dynamic: license-file
